LICENSE.txt
setup.cfg
setup.py
dl2050nn/__config__.py
dl2050nn/__init__.py
dl2050nn/__version__.py
dl2050nn/cbs.py
dl2050nn/data.py
dl2050nn/etc.py
dl2050nn/learner.py
dl2050nn/log.py
dl2050nn/loss.py
dl2050nn/metrics.py
dl2050nn/models.py
dl2050nn/optimizers.py
dl2050nn/results.py
dl2050nn/runner.py
dl2050nn/tabular.py
dl2050nn/transforms.py
dl2050nn.egg-info/PKG-INFO
dl2050nn.egg-info/SOURCES.txt
dl2050nn.egg-info/dependency_links.txt
dl2050nn.egg-info/top_level.txt